<root><unk-0><face0>20190320135920.png</face0></unk-0><unk-1><face1>20190320142718.png</face1></unk-1><unk-2><face2>20190320145041.png</face2></unk-2><unk-3><face3>20190320151316.png</face3></unk-3><unk-4><face4>20190320151322.png</face4></unk-4><unk-5><face5>20190320151334.png</face5></unk-5><unk-6><face6>20190320151335.png</face6></unk-6><unk-7><face7>20190320151522.png</face7></unk-7><unk-8><face8>20190320153255.png</face8><face120>20190410101043.png</face120></unk-8><unk-9><face9>20190327090604.png</face9></unk-9><unk-10><face10>20190327093354.png</face10></unk-10><unk-11><face11>20190327093938.png</face11></unk-11><unk-12><face12>20190327095719.png</face12><face13>20190327095756.png</face13><face14>20190327095757.png</face14><face15>20190327095800.png</face15></unk-12><unk-13><face16>20190327095827.png</face16></unk-13><unk-14><face17>20190327100719.png</face17></unk-14><unk-15><face18>20190327102532.png</face18></unk-15><unk-16><face19>20190327102534.png</face19></unk-16><unk-17><face20>20190327102722.png</face20></unk-17><unk-18><face21>20190328114233.png</face21></unk-18><unk-20><face24>20190401100255.png</face24></unk-20><unk-21><face25>20190401100841.png</face25></unk-21><unk-22><face26>20190401101024.png</face26><face27>20190401101025.png</face27><face28>20190401101039.png</face28></unk-22><unk-23><face29>20190401101205.png</face29></unk-23><unk-24><face30>20190401101231.png</face30></unk-24><unk-25><face31>20190401101325.png</face31></unk-25><unk-26><face32>20190401101329.png</face32></unk-26><unk-27><face33>20190401101457.png</face33></unk-27><unk-28><face34>20190401101458.png</face34></unk-28><unk-30><face36>20190401102453.png</face36></unk-30><unk-31><face37>20190401103336.png</face37></unk-31><unk-32><face38>20190401103637.png</face38></unk-32><unk-33><face39>20190401103639.png</face39></unk-33><unk-34><face40>20190401104646.png</face40></unk-34><unk-35><face41>20190401105047.png</face41></unk-35><unk-36><face42>20190401105200.png</face42><face43>20190401105202.png</face43><face44>20190401105204.png</face44><face45>20190401105206.png</face45><face46>20190401105218.png</face46><face47>20190401105238.png</face47></unk-36><unk-39><face50>20190401110842.png</face50></unk-39><unk-40><face51>20190401112216.png</face51></unk-40><unk-42><face53>20190401112822.png</face53></unk-42><unk-43><face54>20190401112824.png</face54></unk-43><unk-44><face55>20190401112829.png</face55></unk-44><unk-45><face56>20190401112854.png</face56></unk-45><unk-46><face57>20190401113024.png</face57></unk-46><unk-47><face58>20190401113203.png</face58></unk-47><unk-48><face59>20190401113330.png</face59></unk-48><unk-49><face60>20190401114241.png</face60><face97>20190401124315.png</face97><face98>20190401124316.png</face98></unk-49><unk-50><face61>20190401114242.png</face61></unk-50><unk-51><face62>20190401114255.png</face62></unk-51><unk-52><face63>20190401114339.png</face63></unk-52><unk-53><face64>20190401114410.png</face64></unk-53><unk-54><face65>20190401114412.png</face65></unk-54><unk-55><face66>20190401114419.png</face66></unk-55><unk-56><face67>20190401114954.png</face67></unk-56><unk-57><face68>20190401115111.png</face68><face69>20190401115113.png</face69></unk-57><unk-58><face70>20190401115238.png</face70></unk-58><unk-59><face71>20190401115408.png</face71><face108>20190401125543.png</face108></unk-59><unk-60><face73>20190401120142.png</face73></unk-60><unk-61><face74>20190401120150.png</face74></unk-61><unk-62><face75>20190401120152.png</face75></unk-62><unk-63><face76>20190401120153.png</face76></unk-63><unk-64><face77>20190401120158.png</face77></unk-64><unk-65><face78>20190401120238.png</face78></unk-65><unk-66><face79>20190401120257.png</face79></unk-66><unk-67><face80>20190401120332.png</face80></unk-67><unk-68><face81>20190401120516.png</face81></unk-68><unk-69><face82>20190401120721.png</face82><face130>20190410111729.png</face130></unk-69><unk-70><face83>20190401120751.png</face83></unk-70><unk-71><face84>20190401120845.png</face84></unk-71><unk-72><face85>20190401122258.png</face85></unk-72><unk-73><face86>20190401122502.png</face86></unk-73><unk-74><face87>20190401122505.png</face87></unk-74><unk-75><face88>20190401122507.png</face88></unk-75><unk-76><face89>20190401123056.png</face89><face90>20190401123058.png</face90></unk-76><unk-77><face91>20190401123059.png</face91></unk-77><unk-78><face92>20190401123113.png</face92></unk-78><unk-79><face93>20190401123433.png</face93></unk-79><unk-80><face94>20190401123542.png</face94></unk-80><unk-81><face95>20190401123635.png</face95></unk-81><unk-82><face96>20190401124132.png</face96></unk-82><unk-83><face99>20190401124432.png</face99></unk-83><unk-84><face100>20190401124433.png</face100></unk-84><unk-85><face101>20190401124510.png</face101></unk-85><unk-86><face102>20190401124512.png</face102></unk-86><unk-87><face103>20190401124530.png</face103></unk-87><unk-88><face104>20190401124533.png</face104></unk-88><unk-89><face105>20190401124649.png</face105></unk-89><unk-90><face106>20190401124935.png</face106></unk-90><unk-91><face107>20190401125214.png</face107></unk-91><unk-92><face109>20190401125559.png</face109></unk-92><unk-93><face110>20190401125620.png</face110></unk-93><unk-94><face111>20190402145750.png</face111></unk-94><unk-95><face112>20190402145832.png</face112></unk-95><unk-96><face113>20190410095457.png</face113></unk-96><unk-97><face114>20190410095505.png</face114></unk-97><unk-98><face115>20190410095510.png</face115></unk-98><unk-99><face116>20190410100447.png</face116><face117>20190410100452.png</face117></unk-99><unk-100><face118>20190410100813.png</face118></unk-100><unk-101><face119>20190410101008.png</face119></unk-101><unk-102><face121>20190410101143.png</face121></unk-102><unk-103><face122>20190410101934.png</face122></unk-103><unk-104><face123>20190410102850.png</face123></unk-104><unk-105><face124>20190410110005.png</face124></unk-105><unk-106><face125>20190410110012.png</face125></unk-106><unk-107><face126>20190410110245.png</face126></unk-107><unk-108><face127>20190410111106.png</face127></unk-108><unk-109><face128>20190410111432.png</face128></unk-109><unk-110><face129>20190410111608.png</face129></unk-110><unk-111><face131>20190410111919.png</face131></unk-111><unk-112><face132>20190410111958.png</face132></unk-112><unk-113><face133>20190417083542.png</face133><face134>20190417083556.png</face134><face135>20190417083557.png</face135><face136>20190417083655.png</face136></unk-113><unk-114><face139>20190417083802.png</face139></unk-114><unk-115><face138>20190417083712.png</face138></unk-115><unk-116><face140>20190417104607.png</face140><face148>20190417104635.png</face148><face156>20190417104653.png</face156></unk-116><unk-117><face141>20190417104616.png</face141><face147>20190417104634.png</face147><face151>20190417104644.png</face151><face152>20190417104645.png</face152><face157>20190417104655.png</face157><face160>20190417104658.png</face160></unk-117><unk-118><face142>20190417104621.png</face142><face143>20190417104623.png</face143><face145>20190417104628.png</face145><face150>20190417104641.png</face150><face153>20190417104646.png</face153><face154>20190417104649.png</face154></unk-118><unk-119/><unk-120><face146>20190417104630.png</face146><face149>20190417104639.png</face149><face155>20190417104650.png</face155><face158>20190417104656.png</face158><face318>20190417111323.png</face318><face319>20190417111324.png</face319><face320>20190417111325.png</face320><face321>20190417111327.png</face321><face322>20190417111328.png</face322><face323>20190417111329.png</face323><face324>20190417111335.png</face324><face325>20190417111337.png</face325><face327>20190417111340.png</face327><face328>20190417111344.png</face328><face330>20190417111347.png</face330></unk-120><unk-121/><unk-122><face161>20190417104757.png</face161><face162>20190417104758.png</face162><face163>20190417104759.png</face163><face164>20190417104801.png</face164><face165>20190417104803.png</face165><face166>20190417104816.png</face166><face167>20190417104818.png</face167><face185>20190417105214.png</face185><face186>20190417105217.png</face186></unk-122><unk-123><face168>20190417104841.png</face168><face169>20190417104842.png</face169><face170>20190417104844.png</face170><face171>20190417104847.png</face171><face172>20190417104848.png</face172><face173>20190417104850.png</face173><face175>20190417105005.png</face175><face176>20190417105007.png</face176><face177>20190417105012.png</face177><face178>20190417105030.png</face178><face179>20190417105039.png</face179><face183>20190417105212.png</face183><face184>20190417105213.png</face184></unk-123><unk-124><face174>20190417104905.png</face174></unk-124><unk-125/><unk-126><face182>20190417105059.png</face182></unk-126><unk-127/><unk-129/><grp-1430><face336>20190417111524.png</face336><face331>20190417111349.png</face331><face332>20190417111350.png</face332><face333>20190417111433.png</face333><face334>20190417111435.png</face334><face335>20190417111439.png</face335><face306>20190417111242.png</face306><face307>20190417111243.png</face307><face308>20190417111244.png</face308><face309>20190417111245.png</face309><face310>20190417111254.png</face310><face311>20190417111255.png</face311><face312>20190417111256.png</face312><face313>20190417111258.png</face313><face314>20190417111300.png</face314><face315>20190417111301.png</face315><face316>20190417111302.png</face316><face317>20190417111307.png</face317><face326>20190417111339.png</face326><face279>20190417111052.png</face279><face280>20190417111054.png</face280><face281>20190417111055.png</face281><face282>20190417111056.png</face282><face283>20190417111057.png</face283><face284>20190417111059.png</face284><face285>20190417111100.png</face285><face286>20190417111101.png</face286><face287>20190417111102.png</face287><face288>20190417111104.png</face288><face289>20190417111105.png</face289><face290>20190417111107.png</face290><face291>20190417111108.png</face291><face292>20190417111109.png</face292><face293>20190417111111.png</face293><face294>20190417111112.png</face294><face295>20190417111115.png</face295><face296>20190417111116.png</face296><face297>20190417111117.png</face297><face298>20190417111119.png</face298><face299>20190417111120.png</face299><face300>20190417111121.png</face300><face301>20190417111122.png</face301><face302>20190417111124.png</face302><face303>20190417111125.png</face303><face269>20190417111003.png</face269><face270>20190417111013.png</face270><face271>20190417111014.png</face271><face272>20190417111041.png</face272><face273>20190417111042.png</face273><face274>20190417111046.png</face274><face275>20190417111048.png</face275><face276>20190417111049.png</face276><face277>20190417111050.png</face277><face278>20190417111051.png</face278><face253>20190417110918.png</face253><face254>20190417110919.png</face254><face255>20190417110921.png</face255><face256>20190417110922.png</face256><face257>20190417110923.png</face257><face258>20190417110924.png</face258><face259>20190417110927.png</face259><face260>20190417110929.png</face260><face261>20190417110930.png</face261><face262>20190417110932.png</face262><face263>20190417110934.png</face263><face264>20190417110940.png</face264><face265>20190417110941.png</face265><face266>20190417110943.png</face266><face267>20190417110944.png</face267><face268>20190417110948.png</face268><face250>20190417110911.png</face250><face251>20190417110913.png</face251><face252>20190417110914.png</face252><face230>20190417110757.png</face230><face231>20190417110758.png</face231><face232>20190417110759.png</face232><face233>20190417110801.png</face233><face234>20190417110802.png</face234><face235>20190417110803.png</face235><face236>20190417110804.png</face236><face237>20190417110806.png</face237><face238>20190417110807.png</face238><face239>20190417110808.png</face239><face240>20190417110809.png</face240><face241>20190417110814.png</face241><face242>20190417110816.png</face242><face243>20190417110818.png</face243><face244>20190417110821.png</face244><face246>20190417110823.png</face246><face247>20190417110828.png</face247><face248>20190417110829.png</face248><face213>20190417110719.png</face213><face214>20190417110721.png</face214><face215>20190417110722.png</face215><face217>20190417110726.png</face217><face218>20190417110731.png</face218><face219>20190417110733.png</face219><face220>20190417110734.png</face220><face221>20190417110736.png</face221><face222>20190417110737.png</face222><face223>20190417110738.png</face223><face224>20190417110739.png</face224><face225>20190417110741.png</face225><face226>20190417110742.png</face226><face227>20190417110743.png</face227><face228>20190417110744.png</face228><face229>20190417110746.png</face229><face189>20190417105501.png</face189><face190>20190417105917.png</face190><face191>20190417105919.png</face191><face192>20190417105924.png</face192><face193>20190417105930.png</face193><face194>20190417110118.png</face194><face195>20190417110120.png</face195><face196>20190417110121.png</face196><face197>20190417110123.png</face197><face198>20190417110124.png</face198><face199>20190417110126.png</face199><face200>20190417110127.png</face200><face201>20190417110129.png</face201><face202>20190417110130.png</face202><face203>20190417110132.png</face203><face204>20190417110134.png</face204><face205>20190417110135.png</face205><face206>20190417110137.png</face206><face207>20190417110139.png</face207><face208>20190417110141.png</face208></grp-1430><unk-130/><unk-133/><grp-201512185/><grp-201512461/><grp-201512530><face159>20190417104657.png</face159><face144>20190417104626.png</face144></grp-201512530></root>
